ansible_pygments/__init__.py
ansible_pygments/lexers.py
ansible_pygments/styles.py
ansible_pygments-0.1.1.dist-info/entry_points.txt
ansible_pygments-0.1.1.dist-info/LICENSE.md
ansible_pygments-0.1.1.dist-info/WHEEL
ansible_pygments-0.1.1.dist-info/METADATA
ansible_pygments-0.1.1.dist-info/RECORD
