Metadata-Version: 2.1
Name: ansible-pygments
Version: 0.1.1
Summary: Tools for building the Ansible Distribution
Home-page: https://github.com/ansible-community/ansible-pygments
License: BSD-2-Clause
Author: Felix Fontein
Author-email: felix@fontein.de
Requires-Python: >=3.6.0,<4.0.0
Classifier: Development Status :: 6 - Mature
Classifier: Intended Audience :: Developers
Classifier: License :: OSI Approved :: BSD License
Classifier: Programming Language :: Python :: 3
Classifier: Programming Language :: Python :: 3.10
Classifier: Programming Language :: Python :: 3.6
Classifier: Programming Language :: Python :: 3.7
Classifier: Programming Language :: Python :: 3.8
Classifier: Programming Language :: Python :: 3.9
Requires-Dist: pygments (>=2.4.0)
Project-URL: Bug tracker, https://github.com/ansible-community/ansible-pygments/issues
Project-URL: Code of Conduct, https://docs.ansible.com/ansible/latest/community/code_of_conduct.html
Project-URL: CI: GitHub, https://github.com/ansible-community/ansible-pygments/actions?branch:main+event:push
Project-URL: CI: CodeCov, https://app.codecov.io/gh/ansible-community/ansible-pygments
Project-URL: Mailing lists, https://docs.ansible.com/ansible/latest/community/communication.html#mailing-list-information
Project-URL: Repository, https://github.com/ansible-community/ansible-pygments
